README
setup.cfg
setup.py
streamhut/__init__.py
streamhut.egg-info/PKG-INFO
streamhut.egg-info/SOURCES.txt
streamhut.egg-info/dependency_links.txt
streamhut.egg-info/top_level.txt