Metadata-Version: 1.1
Name: streamhut
Version: 0.0.1
Summary: Streamhut python package
Home-page: https://github.com/miguelmota/py-streamhut
Author: Miguel Mota
Author-email: hello@miguelmota.com
License: MIT License
Download-URL: https://github.com/miguelmota/py-streamhut/archive/master.zip
Keywords: streamhut
Platform: UNKNOWN
